minio_driver/MinioDriver.py
minio_driver/MinioProvider.py
minio_driver/__init__.py
minio_driver/integration.py
minio_driver-0.1.6.dist-info/LICENSE
minio_driver-0.1.6.dist-info/METADATA
minio_driver-0.1.6.dist-info/WHEEL
minio_driver-0.1.6.dist-info/top_level.txt
minio_driver-0.1.6.dist-info/RECORD
