Metadata-Version: 2.1
Name: minio-driver
Version: 0.1.6
Summary: Minio Storage Driver for Masonite
Home-page: https://github.com/yubarajshrestha/minio-masonite-driver
Author: Yubaraj Shrestha
Author-email: companion.krish@outlook.com
License: MIT
Keywords: masonite,storage,minio,masonite-storage-driver
Platform: UNKNOWN
Classifier: Programming Language :: Python :: 3
Classifier: Framework :: Masonite
License-File: LICENSE
Requires-Dist: masonite (<5.0,>=4.0)
